slippi/__init__.py
slippi/event.py
slippi/game.py
slippi/id.py
slippi/log.py
slippi/metadata.py
slippi/parse.py
slippi/util.py
test/__init__.py
test/replays.py
py_slippi-1.6.2.dist-info/LICENSE
py_slippi-1.6.2.dist-info/METADATA
py_slippi-1.6.2.dist-info/WHEEL
py_slippi-1.6.2.dist-info/top_level.txt
py_slippi-1.6.2.dist-info/RECORD
