Metadata-Version: 2.1
Name: py-slippi
Version: 1.6.2
Summary: Parsing library for SSBM replay files
Home-page: https://github.com/hohav/py-slippi
Author: melkor
Author-email: hohav@fastmail.com
License: UNKNOWN
Platform: UNKNOWN
Classifier: Programming Language :: Python :: 3
Classifier: License :: OSI Approved :: MIT License
Classifier: Operating System :: OS Independent
Requires-Python: ~=3.7
License-File: LICENSE
